LICENSE.txt
MANIFEST.in
README.rst
setup.cfg
setup.py
TelethonFakeTLS/Connection.py
TelethonFakeTLS/__init__.py
TelethonFakeTLS.egg-info/PKG-INFO
TelethonFakeTLS.egg-info/SOURCES.txt
TelethonFakeTLS.egg-info/dependency_links.txt
TelethonFakeTLS.egg-info/requires.txt
TelethonFakeTLS.egg-info/top_level.txt
TelethonFakeTLS/FakeTLS/EncryptionHelper.py
TelethonFakeTLS/FakeTLS/FakeTLSHello.py
TelethonFakeTLS/FakeTLS/TLSInOut.py
TelethonFakeTLS/FakeTLS/__init__.py
TelethonFakeTLS/FakeTLS/__pycache__/EncryptionHelper.cpython-310.pyc
TelethonFakeTLS/FakeTLS/__pycache__/FakeTLSHello.cpython-310.pyc
TelethonFakeTLS/FakeTLS/__pycache__/TLSInOut.cpython-310.pyc
TelethonFakeTLS/FakeTLS/__pycache__/__init__.cpython-310.pyc
TelethonFakeTLS/__pycache__/Connection.cpython-310.pyc
TelethonFakeTLS/__pycache__/__init__.cpython-310.pyc