Metadata-Version: 2.1
Name: TelethonFakeTLS
Version: 2022.4.4.16.37.38.728726
Summary: MTProxy FakeTLS Support For Telethon !
Home-page: https://github.com/Ro0tz5/telethon-faketls
Author: Ro0tz5
Author-email: Ro0tz5c@Gmail.Com
License: MIT
Download-URL: https://github.com/Ro0tz5/telethon-faketls/archive/refs/heads/master.zip
Keywords: Telethon,FakeTLS,MTProxy,EE
Platform: UNKNOWN
Classifier: Development Status :: 3 - Alpha
Classifier: Intended Audience :: Developers
Classifier: Topic :: Software Development :: Build Tools
Classifier: License :: OSI Approved :: MIT License
Classifier: Programming Language :: Python :: 3
Classifier: Programming Language :: Python :: 3.4
Classifier: Programming Language :: Python :: 3.5
Classifier: Programming Language :: Python :: 3.6
Classifier: Programming Language :: Python :: 3.7
Classifier: Programming Language :: Python :: 3.8
Classifier: Programming Language :: Python :: 3.9
Classifier: Programming Language :: Python :: 3.10
License-File: LICENSE.txt
